zerotheorem/__init__.py
zerotheorem/test.py
zerotheorem_python-3.1.dist-info/LICENSE.txt
zerotheorem_python-3.1.dist-info/METADATA
zerotheorem_python-3.1.dist-info/WHEEL
zerotheorem_python-3.1.dist-info/top_level.txt
zerotheorem_python-3.1.dist-info/RECORD
