Metadata-Version: 2.1
Name: zerotheorem-python
Version: 3.1
Summary: This package for serving api's in python
Home-page: UNKNOWN
Author: Sorez
Author-email: sorez@zerotheorem.com
License: UNKNOWN
Platform: UNKNOWN
Classifier: Programming Language :: Python :: 3
Classifier: License :: OSI Approved :: MIT License
Classifier: Operating System :: OS Independent
License-File: LICENSE.txt
